[{"timestamp":"2026-07-18T03:20:56.066Z","company_name":"Concentrix","branch":"Smart Village","account":"zbsdxzcbx","job_title":"xbcxzcb","employment_status":"Current Employee","duration_text":"من ٦ شهور لسنة","duration_score":2,"pros":"vvvvvvvvvvvvvvvvvvvvvvvvvvvv","cons":"vvvvvvvvvvvvvvvvvvvvvvvvvvvvvvvvv","benefits":["🚌 مواصلات, 🏥 تأمين طبي, 💰 بونص, 🏠 شغل من البيت"],"salary_rating":5,"management_rating":5,"training_rating":5,"career_rating":5,"culture_rating":5,"work_life_rating":5,"would_recommend":0}]